f_tools_pkg/__init__.py
f_tools_pkg/f_bmp.py
f_tools_pkg/f_crypt.py
f_tools_pkg/f_e.py
f_tools_pkg/f_ecc.py
f_tools_pkg/f_excel.py
f_tools_pkg/f_log.py
f_tools_pkg/f_serial.py
f_tools_pkg/f_stil.py
f_tools_pkg-0.0.21.dist-info/METADATA
f_tools_pkg-0.0.21.dist-info/WHEEL
f_tools_pkg-0.0.21.dist-info/top_level.txt
f_tools_pkg-0.0.21.dist-info/RECORD
