Metadata-Version: 2.1
Name: f-tools-pkg
Version: 0.0.21
Summary: some common tools(bmp/crypt/excel/log ...)
Home-page: 
Author: wushengyan
Author-email: WUSY1991@163.com
License: MIT
Classifier: Programming Language :: Python :: 3
Classifier: License :: OSI Approved :: MIT License
Classifier: Operating System :: OS Independent
Requires-Python: >=3.6
Requires-Dist: Crypto
Requires-Dist: xlwt
Requires-Dist: openpyxl
Requires-Dist: pyserial
